{
    "created_time": "2025-06-03T04:07:38Z",
    "files": [
        {
            "attachment_folder": "",
            "created_time": "2025-06-03T04:07:48Z",
            "id": "713",
            "modified_time": "2025-06-03T04:07:48Z",
            "name": "README.md",
            "signature": "3902112209756386580",
            "tags": [
            ]
        }
    ],
    "folders": [
    ],
    "id": "712",
    "modified_time": "2025-06-03T04:07:38Z",
    "signature": "1913909459743044874",
    "version": 3
}
